spotifyconnector/__init__.py
spotifyconnector/__main__.py
spotifyconnector/connector.py
spotifyconnector-0.8.2.dist-info/LICENSE
spotifyconnector-0.8.2.dist-info/METADATA
spotifyconnector-0.8.2.dist-info/WHEEL
spotifyconnector-0.8.2.dist-info/entry_points.txt
spotifyconnector-0.8.2.dist-info/top_level.txt
spotifyconnector-0.8.2.dist-info/RECORD
