Metadata-Version: 2.1
Name: spotifyconnector
Version: 0.8.2
Summary: Spotify Connector for Podcast Data
Author: Open Podcast
License: MIT
License-File: LICENSE
Requires-Dist: requests
Requires-Dist: loguru
Requires-Dist: PyYAML
Requires-Dist: tenacity
Requires-Dist: myst-parser[docs]
